osdu_client/__init__.py
osdu_client/auth.py
osdu_client/client.py
osdu_client/exceptions.py
osdu_client/services/__init__.py
osdu_client/services/base.py
osdu_client/services/dataset/__init__.py
osdu_client/services/dataset/client.py
osdu_client/services/dataset/method_names.json
osdu_client/services/dataset/models.py
osdu_client/services/dataset/swagger.yaml
osdu_client/services/entitlements/__init__.py
osdu_client/services/entitlements/client.py
osdu_client/services/entitlements/method_names.json
osdu_client/services/entitlements/swagger.yaml
osdu_client/services/file/__init__.py
osdu_client/services/file/client.py
osdu_client/services/file/method_names.json
osdu_client/services/file/models.py
osdu_client/services/file/swagger.yaml
osdu_client/services/indexer/__init__.py
osdu_client/services/indexer/client.py
osdu_client/services/indexer/method_names.json
osdu_client/services/indexer/models.py
osdu_client/services/indexer/swagger.yaml
osdu_client/services/legal/__init__.py
osdu_client/services/legal/client.py
osdu_client/services/legal/method_names.json
osdu_client/services/legal/models.py
osdu_client/services/legal/swagger.yaml
osdu_client/services/notification/__init__.py
osdu_client/services/notification/client.py
osdu_client/services/notification/method_names.json
osdu_client/services/notification/models.py
osdu_client/services/notification/swagger.yaml
osdu_client/services/partition/__init__.py
osdu_client/services/partition/client.py
osdu_client/services/partition/method_names.json
osdu_client/services/partition/models.py
osdu_client/services/partition/swagger.yaml
osdu_client/services/policy/__init__.py
osdu_client/services/policy/client.py
osdu_client/services/policy/method_names.json
osdu_client/services/policy/models.py
osdu_client/services/policy/swagger.yaml
osdu_client/services/pws/__init__.py
osdu_client/services/pws/client.py
osdu_client/services/pws/method_names.json
osdu_client/services/pws/models.py
osdu_client/services/pws/swagger.yaml
osdu_client-1.4.0.dist-info/LICENSE
osdu_client-1.4.0.dist-info/METADATA
osdu_client-1.4.0.dist-info/WHEEL
osdu_client-1.4.0.dist-info/RECORD
